[
	{
		"name": "RUINS_RANDOM",
		"spawnWeight": 20,
		"needsRoad": false,
		"income": 1,
		"mapImage":{ "src": "ui", "x": 368, "y": 384, "w": 16, "h": 16 },
		"mapBackground": { "src": "ui", "x": 368, "y": 384, "w": 16, "h": 16 },
		"mapFleetImage": { "src": "ui", "x": 368, "y": 384, "w": 16, "h": 16 },
		"mapFleetBackground": { "src": "ui", "x": 368, "y": 384, "w": 16, "h": 16 },
		"baseConstructions": ["DRONEDRONEMINAIR", "DroneDroneMIN"],
        	"additionalConstructions": ["DRONEDRONEMINAIR", "DroneDroneMIN"],
		"incomeModifierPercentage": -1,
        	"rewards": [
            	{
			"name": "RUINSCleared0",
		        "spawnWeight": 5,
		        "money": 0,
		        "rep": 1
		},
		{
		        "name": "RUINSCleared1",
		        "spawnWeight": 19,
		        "money": 205,
			"bonus": "EXTRA_INCOME",
		        "rep": 5
            	},
		{
		        "name": "RUINSCleared2",
		        "spawnWeight": 10,
		        "money": 95,
		        "rep": 5
            	},
		{
		        "name": "RUINSCleared3",
		        "spawnWeight": 20,
		        "money": -336,
			"bonus": "MECH_SPIDERS",
		        "rep": 5
            	},
		{
		        "name": "RUINSCleared4",
		        "spawnWeight": 21,
		        "money": 207,
			"bonus": "IMPERIAL_CANNON",
		        "rep": 5
            	},
		{
		        "name": "RUINSCleared5",
		        "spawnWeight": 8,
		        "money": -194,
		        "rep": 15
            	},
		{
		        "name": "RUINSCleared6",
		        "spawnWeight": 9,
		        "money": 593,
		        "rep": 5
            	},
		{
		        "name": "RUINSCleared7",
		        "spawnWeight": 10,
		        "money": 1,
		        "rep": 1
            	},
		{
		        "name": "RUINSCleared8",
		        "spawnWeight": 18,
		        "money": 200,
			"bonus": "CE_SUSPENDIUM_SPECIALISTS",
		        "rep": 5
            	},
		{
		        "name": "RUINSCleared9",
		        "spawnWeight": 7,
		        "money": -2560,
		        "rep": -10
            	},
		{
		        "name": "RUINSCleared10",
		        "spawnWeight": 17,
		        "money": 211,
			"bonus": "CEDRONE",
		        "rep": 5
            	},
		{
			"name": "RUINSCleared11",
			"spawnWeight": 20,
			"money": 77,
			"bonus": "TELESCOPES",
		        "rep": -15
		}
       	]
	}
]
