{
    "assignJobsMs": 300,
    "boarders": [],
    "captured": false,
    "carrying": [],
    "chunkSubIDCounter": 1,
    "commandPoints": 34640,
    "constructionBonuses": [],
    "crew": [
        {
            "giveResourceWait": 0,
            "hp": 5,
            "jobIndex": 2,
            "jobModule": 0,
            "msSinceMoved": 0,
            "msUntilRecalcJumpPoint": 0,
            "msUntilRecalcWalkPoint": 0,
            "occupied": false,
            "tile": 0,
            "type": "sailor",
            "weaponReload": 0
        },
        {
            "giveResourceWait": 0,
            "hp": 5,
            "jobIndex": 4,
            "jobModule": 1,
            "msSinceMoved": 0,
            "msUntilRecalcJumpPoint": 0,
            "msUntilRecalcWalkPoint": 0,
            "occupied": false,
            "tile": 1,
            "type": "sailor",
            "weaponReload": 0
        },
        {
            "giveResourceWait": 0,
            "hp": 5,
            "jobIndex": 4,
            "jobModule": 5,
            "msSinceMoved": 0,
            "msUntilRecalcJumpPoint": 0,
            "msUntilRecalcWalkPoint": 0,
            "occupied": false,
            "tile": 7,
            "type": "sailor",
            "weaponReload": 0
        },
        {
            "giveResourceWait": 0,
            "hp": 5,
            "jobIndex": 2,
            "jobModule": 23,
            "msSinceMoved": 0,
            "msUntilRecalcJumpPoint": 0,
            "msUntilRecalcWalkPoint": 0,
            "occupied": false,
            "tile": 109,
            "type": "sailor",
            "weaponReload": 0
        },
        {
            "giveResourceWait": 0,
            "hp": 5,
            "jobIndex": 2,
            "jobModule": 26,
            "msSinceMoved": 0,
            "msUntilRecalcJumpPoint": 0,
            "msUntilRecalcWalkPoint": 0,
            "occupied": false,
            "tile": 112,
            "type": "sailor",
            "weaponReload": 0
        },
        {
            "giveResourceWait": 0,
            "hp": 5,
            "jobIndex": 2,
            "jobModule": 27,
            "msSinceMoved": 0,
            "msUntilRecalcJumpPoint": 0,
            "msUntilRecalcWalkPoint": 0,
            "occupied": false,
            "tile": 113,
            "type": "sailor",
            "weaponReload": 0
        },
        {
            "giveResourceWait": 0,
            "hp": 5,
            "jobIndex": 2,
            "jobModule": 28,
            "msSinceMoved": 0,
            "msUntilRecalcJumpPoint": 0,
            "msUntilRecalcWalkPoint": 0,
            "occupied": false,
            "tile": 114,
            "type": "sailor",
            "weaponReload": 0
        },
        {
            "giveResourceWait": 0,
            "hp": 5,
            "jobIndex": 2,
            "jobModule": 29,
            "msSinceMoved": 0,
            "msUntilRecalcJumpPoint": 0,
            "msUntilRecalcWalkPoint": 0,
            "occupied": false,
            "tile": 115,
            "type": "sailor",
            "weaponReload": 0
        },
        {
            "giveResourceWait": 0,
            "hp": 5,
            "jobIndex": 4,
            "jobModule": 30,
            "msSinceMoved": 0,
            "msUntilRecalcJumpPoint": 0,
            "msUntilRecalcWalkPoint": 0,
            "occupied": false,
            "tile": 116,
            "type": "sailor",
            "weaponReload": 0
        },
        {
            "giveResourceWait": 0,
            "hp": 5,
            "jobIndex": 4,
            "jobModule": 33,
            "msSinceMoved": 0,
            "msUntilRecalcJumpPoint": 0,
            "msUntilRecalcWalkPoint": 0,
            "occupied": false,
            "tile": 120,
            "type": "sailor",
            "weaponReload": 0
        },
        {
            "giveResourceWait": 0,
            "hp": 5,
            "jobIndex": 5,
            "jobModule": 30,
            "msSinceMoved": 0,
            "msUntilRecalcJumpPoint": 0,
            "msUntilRecalcWalkPoint": 0,
            "occupied": false,
            "tile": 117,
            "type": "sailor",
            "weaponReload": 0
        },
        {
            "giveResourceWait": 0,
            "hp": 5,
            "jobIndex": 5,
            "jobModule": 33,
            "msSinceMoved": 0,
            "msUntilRecalcJumpPoint": 0,
            "msUntilRecalcWalkPoint": 0,
            "occupied": false,
            "tile": 121,
            "type": "sailor",
            "weaponReload": 0
        },
        {
            "giveResourceWait": 0,
            "hp": 5,
            "jobIndex": 4,
            "jobModule": 3,
            "msSinceMoved": 0,
            "msUntilRecalcJumpPoint": 0,
            "msUntilRecalcWalkPoint": 0,
            "occupied": false,
            "tile": 4,
            "type": "sailor",
            "weaponReload": 0
        },
        {
            "giveResourceWait": 0,
            "hp": 5,
            "jobIndex": 4,
            "jobModule": 7,
            "msSinceMoved": 0,
            "msUntilRecalcJumpPoint": 0,
            "msUntilRecalcWalkPoint": 0,
            "occupied": false,
            "tile": 10,
            "type": "sailor",
            "weaponReload": 0
        },
        {
            "giveResourceWait": 0,
            "hp": 5,
            "jobIndex": 6,
            "jobModule": 9,
            "msSinceMoved": 0,
            "msUntilRecalcJumpPoint": 0,
            "msUntilRecalcWalkPoint": 0,
            "occupied": false,
            "tile": 23,
            "type": "sailor",
            "weaponReload": 0
        },
        {
            "giveResourceWait": 0,
            "hp": 5,
            "jobIndex": 6,
            "jobModule": 10,
            "msSinceMoved": 0,
            "msUntilRecalcJumpPoint": 0,
            "msUntilRecalcWalkPoint": 0,
            "occupied": false,
            "tile": 38,
            "type": "sailor",
            "weaponReload": 0
        },
        {
            "giveResourceWait": 0,
            "hp": 5,
            "jobIndex": 6,
            "jobModule": 11,
            "msSinceMoved": 0,
            "msUntilRecalcJumpPoint": 0,
            "msUntilRecalcWalkPoint": 0,
            "occupied": false,
            "tile": 53,
            "type": "sailor",
            "weaponReload": 0
        },
        {
            "giveResourceWait": 0,
            "hp": 5,
            "jobIndex": 6,
            "jobModule": 20,
            "msSinceMoved": 0,
            "msUntilRecalcJumpPoint": 0,
            "msUntilRecalcWalkPoint": 0,
            "occupied": false,
            "tile": 100,
            "type": "sailor",
            "weaponReload": 0
        },
        {
            "giveResourceWait": 0,
            "hp": 5,
            "jobIndex": 7,
            "jobModule": 9,
            "msSinceMoved": 0,
            "msUntilRecalcJumpPoint": 0,
            "msUntilRecalcWalkPoint": 0,
            "occupied": false,
            "tile": 24,
            "type": "sailor",
            "weaponReload": 0
        },
        {
            "giveResourceWait": 0,
            "hp": 5,
            "jobIndex": 7,
            "jobModule": 10,
            "msSinceMoved": 0,
            "msUntilRecalcJumpPoint": 0,
            "msUntilRecalcWalkPoint": 0,
            "occupied": false,
            "tile": 39,
            "type": "sailor",
            "weaponReload": 0
        },
        {
            "giveResourceWait": 0,
            "hp": 5,
            "jobIndex": 7,
            "jobModule": 11,
            "msSinceMoved": 0,
            "msUntilRecalcJumpPoint": 0,
            "msUntilRecalcWalkPoint": 0,
            "occupied": false,
            "tile": 54,
            "type": "sailor",
            "weaponReload": 0
        }
    ],
    "decals": [],
    "fireMode": "NORMAL",
    "flipMs": 0,
    "flipTo": false,
    "flipped": false,
    "focusOnFirefighting": false,
    "focusOnMoving": false,
    "focusOnRepair": false,
    "focusOnShooting": true,
    "h": 7,
    "modules": [
        {
            "ammoLeft": 0,
            "burntOut": false,
            "fire": 0,
            "hp": 129,
            "lowestHP": 129,
            "msUntilCoal": 0,
            "shootAccumulator": 0,
            "type": "COCKPIT",
            "x": 18,
            "y": 1
        },
        {
            "ammoLeft": 6,
            "burntOut": false,
            "fire": 0,
            "hp": 36,
            "lowestHP": 36,
            "msUntilCoal": 0,
            "shootAccumulator": 0,
            "type": "FLAK_CANNON",
            "x": 29,
            "y": 2
        },
        {
            "ammoLeft": 0,
            "burntOut": false,
            "fire": 0,
            "hp": 65,
            "lowestHP": 65,
            "msUntilCoal": 0,
            "shootAccumulator": 0,
            "type": "BERTH",
            "x": 29,
            "y": 3
        },
        {
            "AMMO": 20,
            "ammoLeft": 0,
            "burntOut": false,
            "fire": 0,
            "hp": 130,
            "lowestHP": 130,
            "msUntilCoal": 0,
            "shootAccumulator": 0,
            "type": "SMALL_AMMO",
            "x": 30,
            "y": 3
        },
        {
            "ammoLeft": 0,
            "burntOut": false,
            "fire": 0,
            "hp": 85,
            "lowestHP": 85,
            "msUntilCoal": 0,
            "shootAccumulator": 0,
            "type": "BERTH",
            "x": 32,
            "y": 3
        },
        {
            "ammoLeft": 6,
            "burntOut": false,
            "fire": 0,
            "hp": 36,
            "lowestHP": 36,
            "msUntilCoal": 0,
            "shootAccumulator": 0,
            "type": "FLAK_CANNON",
            "x": 4,
            "y": 2
        },
        {
            "ammoLeft": 0,
            "burntOut": false,
            "fire": 0,
            "hp": 85,
            "lowestHP": 85,
            "msUntilCoal": 0,
            "shootAccumulator": 0,
            "type": "BERTH",
            "x": 2,
            "y": 3
        },
        {
            "AMMO": 20,
            "ammoLeft": 0,
            "burntOut": false,
            "fire": 0,
            "hp": 130,
            "lowestHP": 130,
            "msUntilCoal": 0,
            "shootAccumulator": 0,
            "type": "SMALL_AMMO",
            "x": 3,
            "y": 3
        },
        {
            "ammoLeft": 0,
            "burntOut": false,
            "fire": 0,
            "hp": 65,
            "lowestHP": 65,
            "msUntilCoal": 0,
            "shootAccumulator": 0,
            "type": "BERTH",
            "x": 5,
            "y": 3
        },
        {
            "AMMO": 5,
            "COAL": 2,
            "REPAIR": 40,
            "WATER": 12,
            "ammoLeft": 0,
            "burntOut": false,
            "fire": 0,
            "hp": 772,
            "lowestHP": 772,
            "msUntilCoal": 0,
            "shootAccumulator": 0,
            "type": "STORAGE",
            "x": 1,
            "y": 4
        },
        {
            "AMMO": 5,
            "COAL": 2,
            "REPAIR": 40,
            "WATER": 12,
            "ammoLeft": 0,
            "burntOut": false,
            "fire": 0,
            "hp": 772,
            "lowestHP": 772,
            "msUntilCoal": 0,
            "shootAccumulator": 0,
            "type": "STORAGE",
            "x": 29,
            "y": 4
        },
        {
            "AMMO": 5,
            "COAL": 2,
            "REPAIR": 40,
            "WATER": 12,
            "ammoLeft": 0,
            "burntOut": false,
            "fire": 0,
            "hp": 909,
            "lowestHP": 909,
            "msUntilCoal": 0,
            "shootAccumulator": 0,
            "type": "STORAGE",
            "x": 15,
            "y": 2
        },
        {
            "ammoLeft": 0,
            "burntOut": false,
            "fire": 0,
            "hp": 127,
            "lowestHP": 127,
            "msUntilCoal": 0,
            "shootAccumulator": 0,
            "type": "HATCH",
            "x": 15,
            "y": 5
        },
        {
            "ammoLeft": 0,
            "burntOut": false,
            "fire": 0,
            "hp": 85,
            "lowestHP": 85,
            "msUntilCoal": 0,
            "shootAccumulator": 0,
            "type": "BERTH",
            "x": 16,
            "y": 5
        },
        {
            "ammoLeft": 0,
            "burntOut": false,
            "fire": 0,
            "hp": 112,
            "lowestHP": 112,
            "msUntilCoal": 0,
            "shootAccumulator": 0,
            "type": "FOUNDATION",
            "x": 19,
            "y": 6
        },
        {
            "ammoLeft": 0,
            "burntOut": false,
            "fire": 0,
            "hp": 161,
            "lowestHP": 161,
            "msUntilCoal": 0,
            "shootAccumulator": 0,
            "type": "FOUNDATION",
            "x": 18,
            "y": 6
        },
        {
            "ammoLeft": 0,
            "burntOut": false,
            "fire": 0,
            "hp": 161,
            "lowestHP": 161,
            "msUntilCoal": 0,
            "shootAccumulator": 0,
            "type": "FOUNDATION",
            "x": 16,
            "y": 6
        },
        {
            "ammoLeft": 0,
            "burntOut": false,
            "fire": 0,
            "hp": 112,
            "lowestHP": 112,
            "msUntilCoal": 0,
            "shootAccumulator": 0,
            "type": "FOUNDATION",
            "x": 15,
            "y": 6
        },
        {
            "ammoLeft": 0,
            "burntOut": false,
            "fire": 0,
            "hp": 174,
            "lowestHP": 174,
            "msUntilCoal": 0,
            "shootAccumulator": 0,
            "type": "TREES",
            "x": 20,
            "y": 4
        },
        {
            "ammoLeft": 0,
            "burntOut": false,
            "fire": 0,
            "hp": 174,
            "lowestHP": 174,
            "msUntilCoal": 0,
            "shootAccumulator": 0,
            "type": "TREES",
            "x": 6,
            "y": 4
        },
        {
            "REPAIR": 50,
            "ammoLeft": 0,
            "burntOut": false,
            "fire": 0,
            "hp": 233,
            "lowestHP": 233,
            "msUntilCoal": 0,
            "shootAccumulator": 0,
            "type": "REPAIR_BAY",
            "x": 17,
            "y": 5
        },
        {
            "ammoLeft": 0,
            "burntOut": false,
            "fire": 0,
            "hp": 251,
            "lowestHP": 251,
            "msUntilCoal": 0,
            "shootAccumulator": 0,
            "type": "FLIPPED_INCLINE_UP",
            "x": 0,
            "y": 4
        },
        {
            "ammoLeft": 0,
            "burntOut": false,
            "fire": 0,
            "hp": 251,
            "lowestHP": 251,
            "msUntilCoal": 0,
            "shootAccumulator": 0,
            "type": "INCLINE_UP",
            "x": 34,
            "y": 4
        },
        {
            "ammoLeft": 0,
            "burntOut": false,
            "fire": 0,
            "hp": 10,
            "lowestHP": 10,
            "msUntilCoal": 0,
            "shootAccumulator": 0,
            "type": "CROWS_NEST",
            "x": 17,
            "y": 0
        },
        {
            "ammoLeft": 0,
            "burntOut": false,
            "fire": 0,
            "hp": 85,
            "lowestHP": 85,
            "msUntilCoal": 0,
            "shootAccumulator": 0,
            "type": "BERTH",
            "x": 17,
            "y": 1
        },
        {
            "ammoLeft": 0,
            "burntOut": false,
            "fire": 0,
            "hp": 65,
            "lowestHP": 65,
            "msUntilCoal": 0,
            "shootAccumulator": 0,
            "type": "BERTH",
            "x": 17,
            "y": 6
        },
        {
            "ammoLeft": 5,
            "burntOut": false,
            "fire": 0,
            "hp": 113,
            "lowestHP": 113,
            "msUntilCoal": 0,
            "shootAccumulator": 0,
            "type": "FLIPPED_SHARPSHOOTER",
            "x": 1,
            "y": 3
        },
        {
            "ammoLeft": 5,
            "burntOut": false,
            "fire": 0,
            "hp": 113,
            "lowestHP": 113,
            "msUntilCoal": 0,
            "shootAccumulator": 0,
            "type": "SHARPSHOOTER",
            "x": 33,
            "y": 3
        },
        {
            "ammoLeft": 50,
            "burntOut": false,
            "fire": 0,
            "hp": 112,
            "lowestHP": 112,
            "msUntilCoal": 0,
            "shootAccumulator": 0,
            "type": "FLIPPED_THIRTY_CAL",
            "x": 15,
            "y": 1
        },
        {
            "ammoLeft": 50,
            "burntOut": false,
            "fire": 0,
            "hp": 112,
            "lowestHP": 112,
            "msUntilCoal": 0,
            "shootAccumulator": 0,
            "type": "THIRTY_CAL",
            "x": 19,
            "y": 1
        },
        {
            "ammoLeft": 4,
            "burntOut": false,
            "fire": 0,
            "hp": 172,
            "lowestHP": 172,
            "msUntilCoal": 0,
            "shootAccumulator": 0,
            "type": "ARMORED_DECK_GUN_TOP",
            "x": 32,
            "y": 2
        },
        {
            "ammoLeft": 0,
            "burntOut": false,
            "fire": 0,
            "hp": 97,
            "lowestHP": 97,
            "msUntilCoal": 0,
            "shootAccumulator": 0,
            "type": "HATCH",
            "x": 16,
            "y": 1
        },
        {
            "ammoLeft": 0,
            "burntOut": false,
            "fire": 0,
            "hp": 97,
            "lowestHP": 97,
            "msUntilCoal": 0,
            "shootAccumulator": 0,
            "type": "HATCH",
            "x": 31,
            "y": 2
        },
        {
            "ammoLeft": 4,
            "burntOut": false,
            "fire": 0,
            "hp": 172,
            "lowestHP": 172,
            "msUntilCoal": 0,
            "shootAccumulator": 0,
            "type": "FLIPPED_ARMORED_DECK_GUN_TOP",
            "x": 1,
            "y": 2
        },
        {
            "ammoLeft": 0,
            "burntOut": false,
            "fire": 0,
            "hp": 97,
            "lowestHP": 97,
            "msUntilCoal": 0,
            "shootAccumulator": 0,
            "type": "HATCH",
            "x": 3,
            "y": 2
        }
    ],
    "moveToX": 0,
    "moveToY": 0,
    "msSinceOnGround": 10000,
    "name": "Farm2-a",
    "networkID": "[no network ID]",
    "ramming": false,
    "sitting": false,
    "tiles": [
        {
            "armour": {
                "hp": 30,
                "type": "STONE_WALL",
                "window": true
            },
            "module": 0,
            "x": 18,
            "y": 1
        },
        {
            "armour": {
                "hp": 30,
                "type": "STONE_WALL",
                "window": true
            },
            "module": 1,
            "x": 29,
            "y": 2
        },
        {
            "armour": {
                "hp": 30,
                "type": "STONE_WALL",
                "window": true
            },
            "module": 1,
            "x": 30,
            "y": 2
        },
        {
            "armour": {
                "hp": 30,
                "type": "STONE_WALL",
                "window": true
            },
            "module": 2,
            "x": 29,
            "y": 3
        },
        {
            "armour": {
                "hp": 60,
                "type": "STONE_WALL",
                "window": false
            },
            "module": 3,
            "x": 30,
            "y": 3
        },
        {
            "armour": {
                "hp": 60,
                "type": "STONE_WALL",
                "window": false
            },
            "module": 3,
            "x": 31,
            "y": 3
        },
        {
            "armour": {
                "hp": 30,
                "type": "STONE_WALL",
                "window": true
            },
            "module": 4,
            "x": 32,
            "y": 3
        },
        {
            "armour": {
                "hp": 30,
                "type": "STONE_WALL",
                "window": true
            },
            "module": 5,
            "x": 4,
            "y": 2
        },
        {
            "armour": {
                "hp": 30,
                "type": "STONE_WALL",
                "window": true
            },
            "module": 5,
            "x": 5,
            "y": 2
        },
        {
            "armour": {
                "hp": 30,
                "type": "STONE_WALL",
                "window": true
            },
            "module": 6,
            "x": 2,
            "y": 3
        },
        {
            "armour": {
                "hp": 60,
                "type": "STONE_WALL",
                "window": false
            },
            "module": 7,
            "x": 3,
            "y": 3
        },
        {
            "armour": {
                "hp": 60,
                "type": "STONE_WALL",
                "window": false
            },
            "module": 7,
            "x": 4,
            "y": 3
        },
        {
            "armour": {
                "hp": 30,
                "type": "STONE_WALL",
                "window": true
            },
            "module": 8,
            "x": 5,
            "y": 3
        },
        {
            "armour": {
                "hp": 30,
                "type": "STONE_WALL",
                "window": true
            },
            "module": 9,
            "x": 1,
            "y": 4
        },
        {
            "armour": {
                "hp": 60,
                "type": "STONE_WALL",
                "window": false
            },
            "module": 9,
            "x": 2,
            "y": 4
        },
        {
            "armour": {
                "hp": 60,
                "type": "STONE_WALL",
                "window": false
            },
            "module": 9,
            "x": 3,
            "y": 4
        },
        {
            "armour": {
                "hp": 60,
                "type": "STONE_WALL",
                "window": false
            },
            "module": 9,
            "x": 4,
            "y": 4
        },
        {
            "armour": {
                "hp": 30,
                "type": "STONE_WALL",
                "window": true
            },
            "module": 9,
            "x": 5,
            "y": 4
        },
        {
            "armour": {
                "hp": 60,
                "type": "STONE_WALL",
                "window": false
            },
            "module": 9,
            "x": 1,
            "y": 5
        },
        {
            "armour": {
                "hp": 60,
                "type": "STONE_WALL",
                "window": false
            },
            "module": 9,
            "x": 2,
            "y": 5
        },
        {
            "armour": {
                "hp": 60,
                "type": "STONE_WALL",
                "window": false
            },
            "module": 9,
            "x": 3,
            "y": 5
        },
        {
            "armour": {
                "hp": 60,
                "type": "STONE_WALL",
                "window": false
            },
            "module": 9,
            "x": 4,
            "y": 5
        },
        {
            "armour": {
                "hp": 60,
                "type": "STONE_WALL",
                "window": false
            },
            "module": 9,
            "x": 5,
            "y": 5
        },
        {
            "armour": {
                "hp": 30,
                "type": "STONE_WALL",
                "window": true
            },
            "module": 9,
            "x": 1,
            "y": 6
        },
        {
            "armour": {
                "hp": 60,
                "type": "STONE_WALL",
                "window": false
            },
            "module": 9,
            "x": 2,
            "y": 6
        },
        {
            "armour": {
                "hp": 60,
                "type": "STONE_WALL",
                "window": false
            },
            "module": 9,
            "x": 3,
            "y": 6
        },
        {
            "armour": {
                "hp": 60,
                "type": "STONE_WALL",
                "window": false
            },
            "module": 9,
            "x": 4,
            "y": 6
        },
        {
            "armour": {
                "hp": 30,
                "type": "STONE_WALL",
                "window": true
            },
            "module": 9,
            "x": 5,
            "y": 6
        },
        {
            "armour": {
                "hp": 30,
                "type": "STONE_WALL",
                "window": true
            },
            "module": 10,
            "x": 29,
            "y": 4
        },
        {
            "armour": {
                "hp": 60,
                "type": "STONE_WALL",
                "window": false
            },
            "module": 10,
            "x": 30,
            "y": 4
        },
        {
            "armour": {
                "hp": 60,
                "type": "STONE_WALL",
                "window": false
            },
            "module": 10,
            "x": 31,
            "y": 4
        },
        {
            "armour": {
                "hp": 60,
                "type": "STONE_WALL",
                "window": false
            },
            "module": 10,
            "x": 32,
            "y": 4
        },
        {
            "armour": {
                "hp": 30,
                "type": "STONE_WALL",
                "window": true
            },
            "module": 10,
            "x": 33,
            "y": 4
        },
        {
            "armour": {
                "hp": 60,
                "type": "STONE_WALL",
                "window": false
            },
            "module": 10,
            "x": 29,
            "y": 5
        },
        {
            "armour": {
                "hp": 60,
                "type": "STONE_WALL",
                "window": false
            },
            "module": 10,
            "x": 30,
            "y": 5
        },
        {
            "armour": {
                "hp": 60,
                "type": "STONE_WALL",
                "window": false
            },
            "module": 10,
            "x": 31,
            "y": 5
        },
        {
            "armour": {
                "hp": 60,
                "type": "STONE_WALL",
                "window": false
            },
            "module": 10,
            "x": 32,
            "y": 5
        },
        {
            "armour": {
                "hp": 60,
                "type": "STONE_WALL",
                "window": false
            },
            "module": 10,
            "x": 33,
            "y": 5
        },
        {
            "armour": {
                "hp": 30,
                "type": "STONE_WALL",
                "window": true
            },
            "module": 10,
            "x": 29,
            "y": 6
        },
        {
            "armour": {
                "hp": 60,
                "type": "STONE_WALL",
                "window": false
            },
            "module": 10,
            "x": 30,
            "y": 6
        },
        {
            "armour": {
                "hp": 60,
                "type": "STONE_WALL",
                "window": false
            },
            "module": 10,
            "x": 31,
            "y": 6
        },
        {
            "armour": {
                "hp": 60,
                "type": "STONE_WALL",
                "window": false
            },
            "module": 10,
            "x": 32,
            "y": 6
        },
        {
            "armour": {
                "hp": 30,
                "type": "STONE_WALL",
                "window": true
            },
            "module": 10,
            "x": 33,
            "y": 6
        },
        {
            "armour": {
                "hp": 30,
                "type": "STONE_WALL",
                "window": true
            },
            "module": 11,
            "x": 15,
            "y": 2
        },
        {
            "armour": {
                "hp": 60,
                "type": "STONE_WALL",
                "window": false
            },
            "module": 11,
            "x": 16,
            "y": 2
        },
        {
            "armour": {
                "hp": 60,
                "type": "STONE_WALL",
                "window": false
            },
            "module": 11,
            "x": 17,
            "y": 2
        },
        {
            "armour": {
                "hp": 60,
                "type": "STONE_WALL",
                "window": false
            },
            "module": 11,
            "x": 18,
            "y": 2
        },
        {
            "armour": {
                "hp": 30,
                "type": "STONE_WALL",
                "window": true
            },
            "module": 11,
            "x": 19,
            "y": 2
        },
        {
            "armour": {
                "hp": 60,
                "type": "STONE_WALL",
                "window": false
            },
            "module": 11,
            "x": 15,
            "y": 3
        },
        {
            "armour": {
                "hp": 60,
                "type": "STONE_WALL",
                "window": false
            },
            "module": 11,
            "x": 16,
            "y": 3
        },
        {
            "armour": {
                "hp": 60,
                "type": "STONE_WALL",
                "window": false
            },
            "module": 11,
            "x": 17,
            "y": 3
        },
        {
            "armour": {
                "hp": 60,
                "type": "STONE_WALL",
                "window": false
            },
            "module": 11,
            "x": 18,
            "y": 3
        },
        {
            "armour": {
                "hp": 60,
                "type": "STONE_WALL",
                "window": false
            },
            "module": 11,
            "x": 19,
            "y": 3
        },
        {
            "armour": {
                "hp": 30,
                "type": "STONE_WALL",
                "window": true
            },
            "module": 11,
            "x": 15,
            "y": 4
        },
        {
            "armour": {
                "hp": 60,
                "type": "STONE_WALL",
                "window": false
            },
            "module": 11,
            "x": 16,
            "y": 4
        },
        {
            "armour": {
                "hp": 60,
                "type": "STONE_WALL",
                "window": false
            },
            "module": 11,
            "x": 17,
            "y": 4
        },
        {
            "armour": {
                "hp": 60,
                "type": "STONE_WALL",
                "window": false
            },
            "module": 11,
            "x": 18,
            "y": 4
        },
        {
            "armour": {
                "hp": 30,
                "type": "STONE_WALL",
                "window": true
            },
            "module": 11,
            "x": 19,
            "y": 4
        },
        {
            "armour": {
                "hp": 0,
                "type": "NONE",
                "window": false
            },
            "module": 12,
            "x": 15,
            "y": 5
        },
        {
            "armour": {
                "hp": 30,
                "type": "STONE_WALL",
                "window": true
            },
            "module": 13,
            "x": 16,
            "y": 5
        },
        {
            "armour": {
                "hp": 60,
                "type": "STONE_WALL",
                "window": false
            },
            "module": 14,
            "x": 19,
            "y": 6
        },
        {
            "armour": {
                "hp": 60,
                "type": "STONE_WALL",
                "window": false
            },
            "module": 15,
            "x": 18,
            "y": 6
        },
        {
            "armour": {
                "hp": 60,
                "type": "STONE_WALL",
                "window": false
            },
            "module": 16,
            "x": 16,
            "y": 6
        },
        {
            "armour": {
                "hp": 60,
                "type": "STONE_WALL",
                "window": false
            },
            "module": 17,
            "x": 15,
            "y": 6
        },
        {
            "armour": {
                "hp": 0,
                "type": "NONE",
                "window": false
            },
            "module": 18,
            "x": 20,
            "y": 4
        },
        {
            "armour": {
                "hp": 0,
                "type": "NONE",
                "window": false
            },
            "module": 18,
            "x": 21,
            "y": 4
        },
        {
            "armour": {
                "hp": 0,
                "type": "NONE",
                "window": false
            },
            "module": 18,
            "x": 22,
            "y": 4
        },
        {
            "armour": {
                "hp": 0,
                "type": "NONE",
                "window": false
            },
            "module": 18,
            "x": 23,
            "y": 4
        },
        {
            "armour": {
                "hp": 0,
                "type": "NONE",
                "window": false
            },
            "module": 18,
            "x": 24,
            "y": 4
        },
        {
            "armour": {
                "hp": 0,
                "type": "NONE",
                "window": false
            },
            "module": 18,
            "x": 25,
            "y": 4
        },
        {
            "armour": {
                "hp": 0,
                "type": "NONE",
                "window": false
            },
            "module": 18,
            "x": 26,
            "y": 4
        },
        {
            "armour": {
                "hp": 0,
                "type": "NONE",
                "window": false
            },
            "module": 18,
            "x": 27,
            "y": 4
        },
        {
            "armour": {
                "hp": 0,
                "type": "NONE",
                "window": false
            },
            "module": 18,
            "x": 28,
            "y": 4
        },
        {
            "armour": {
                "hp": 0,
                "type": "NONE",
                "window": false
            },
            "module": 18,
            "x": 20,
            "y": 5
        },
        {
            "armour": {
                "hp": 0,
                "type": "NONE",
                "window": false
            },
            "module": 18,
            "x": 21,
            "y": 5
        },
        {
            "armour": {
                "hp": 0,
                "type": "NONE",
                "window": false
            },
            "module": 18,
            "x": 22,
            "y": 5
        },
        {
            "armour": {
                "hp": 0,
                "type": "NONE",
                "window": false
            },
            "module": 18,
            "x": 23,
            "y": 5
        },
        {
            "armour": {
                "hp": 0,
                "type": "NONE",
                "window": false
            },
            "module": 18,
            "x": 24,
            "y": 5
        },
        {
            "armour": {
                "hp": 0,
                "type": "NONE",
                "window": false
            },
            "module": 18,
            "x": 25,
            "y": 5
        },
        {
            "armour": {
                "hp": 0,
                "type": "NONE",
                "window": false
            },
            "module": 18,
            "x": 26,
            "y": 5
        },
        {
            "armour": {
                "hp": 0,
                "type": "NONE",
                "window": false
            },
            "module": 18,
            "x": 27,
            "y": 5
        },
        {
            "armour": {
                "hp": 0,
                "type": "NONE",
                "window": false
            },
            "module": 18,
            "x": 28,
            "y": 5
        },
        {
            "armour": {
                "hp": 0,
                "type": "NONE",
                "window": false
            },
            "module": 19,
            "x": 6,
            "y": 4
        },
        {
            "armour": {
                "hp": 0,
                "type": "NONE",
                "window": false
            },
            "module": 19,
            "x": 7,
            "y": 4
        },
        {
            "armour": {
                "hp": 0,
                "type": "NONE",
                "window": false
            },
            "module": 19,
            "x": 8,
            "y": 4
        },
        {
            "armour": {
                "hp": 0,
                "type": "NONE",
                "window": false
            },
            "module": 19,
            "x": 9,
            "y": 4
        },
        {
            "armour": {
                "hp": 0,
                "type": "NONE",
                "window": false
            },
            "module": 19,
            "x": 10,
            "y": 4
        },
        {
            "armour": {
                "hp": 0,
                "type": "NONE",
                "window": false
            },
            "module": 19,
            "x": 11,
            "y": 4
        },
        {
            "armour": {
                "hp": 0,
                "type": "NONE",
                "window": false
            },
            "module": 19,
            "x": 12,
            "y": 4
        },
        {
            "armour": {
                "hp": 0,
                "type": "NONE",
                "window": false
            },
            "module": 19,
            "x": 13,
            "y": 4
        },
        {
            "armour": {
                "hp": 0,
                "type": "NONE",
                "window": false
            },
            "module": 19,
            "x": 14,
            "y": 4
        },
        {
            "armour": {
                "hp": 0,
                "type": "NONE",
                "window": false
            },
            "module": 19,
            "x": 6,
            "y": 5
        },
        {
            "armour": {
                "hp": 0,
                "type": "NONE",
                "window": false
            },
            "module": 19,
            "x": 7,
            "y": 5
        },
        {
            "armour": {
                "hp": 0,
                "type": "NONE",
                "window": false
            },
            "module": 19,
            "x": 8,
            "y": 5
        },
        {
            "armour": {
                "hp": 0,
                "type": "NONE",
                "window": false
            },
            "module": 19,
            "x": 9,
            "y": 5
        },
        {
            "armour": {
                "hp": 0,
                "type": "NONE",
                "window": false
            },
            "module": 19,
            "x": 10,
            "y": 5
        },
        {
            "armour": {
                "hp": 0,
                "type": "NONE",
                "window": false
            },
            "module": 19,
            "x": 11,
            "y": 5
        },
        {
            "armour": {
                "hp": 0,
                "type": "NONE",
                "window": false
            },
            "module": 19,
            "x": 12,
            "y": 5
        },
        {
            "armour": {
                "hp": 0,
                "type": "NONE",
                "window": false
            },
            "module": 19,
            "x": 13,
            "y": 5
        },
        {
            "armour": {
                "hp": 0,
                "type": "NONE",
                "window": false
            },
            "module": 19,
            "x": 14,
            "y": 5
        },
        {
            "armour": {
                "hp": 30,
                "type": "STONE_WALL",
                "window": true
            },
            "module": 20,
            "x": 17,
            "y": 5
        },
        {
            "armour": {
                "hp": 60,
                "type": "STONE_WALL",
                "window": false
            },
            "module": 20,
            "x": 18,
            "y": 5
        },
        {
            "armour": {
                "hp": 60,
                "type": "STONE_WALL",
                "window": false
            },
            "module": 20,
            "x": 19,
            "y": 5
        },
        {
            "armour": {
                "hp": 0,
                "type": "NONE",
                "window": false
            },
            "module": 21,
            "x": 0,
            "y": 4
        },
        {
            "armour": {
                "hp": 0,
                "type": "NONE",
                "window": false
            },
            "module": 21,
            "x": 0,
            "y": 5
        },
        {
            "armour": {
                "hp": 0,
                "type": "NONE",
                "window": false
            },
            "module": 21,
            "x": 0,
            "y": 6
        },
        {
            "armour": {
                "hp": 0,
                "type": "NONE",
                "window": false
            },
            "module": 22,
            "x": 34,
            "y": 4
        },
        {
            "armour": {
                "hp": 0,
                "type": "NONE",
                "window": false
            },
            "module": 22,
            "x": 34,
            "y": 5
        },
        {
            "armour": {
                "hp": 0,
                "type": "NONE",
                "window": false
            },
            "module": 22,
            "x": 34,
            "y": 6
        },
        {
            "armour": {
                "hp": 0,
                "type": "NONE",
                "window": false
            },
            "module": 23,
            "x": 17,
            "y": 0
        },
        {
            "armour": {
                "hp": 30,
                "type": "STONE_WALL",
                "window": true
            },
            "module": 24,
            "x": 17,
            "y": 1
        },
        {
            "armour": {
                "hp": 30,
                "type": "STONE_WALL",
                "window": true
            },
            "module": 25,
            "x": 17,
            "y": 6
        },
        {
            "armour": {
                "hp": 60,
                "type": "STONE_WALL",
                "window": false
            },
            "module": 26,
            "x": 1,
            "y": 3
        },
        {
            "armour": {
                "hp": 60,
                "type": "STONE_WALL",
                "window": false
            },
            "module": 27,
            "x": 33,
            "y": 3
        },
        {
            "armour": {
                "hp": 60,
                "type": "STONE_WALL",
                "window": false
            },
            "module": 28,
            "x": 15,
            "y": 1
        },
        {
            "armour": {
                "hp": 60,
                "type": "STONE_WALL",
                "window": false
            },
            "module": 29,
            "x": 19,
            "y": 1
        },
        {
            "armour": {
                "hp": 0,
                "type": "NONE",
                "window": false
            },
            "module": 30,
            "x": 32,
            "y": 2
        },
        {
            "armour": {
                "hp": 0,
                "type": "NONE",
                "window": false
            },
            "module": 30,
            "x": 33,
            "y": 2
        },
        {
            "armour": {
                "hp": 0,
                "type": "NONE",
                "window": false
            },
            "module": 31,
            "x": 16,
            "y": 1
        },
        {
            "armour": {
                "hp": 0,
                "type": "NONE",
                "window": false
            },
            "module": 32,
            "x": 31,
            "y": 2
        },
        {
            "armour": {
                "hp": 0,
                "type": "NONE",
                "window": false
            },
            "module": 33,
            "x": 1,
            "y": 2
        },
        {
            "armour": {
                "hp": 0,
                "type": "NONE",
                "window": false
            },
            "module": 33,
            "x": 2,
            "y": 2
        },
        {
            "armour": {
                "hp": 0,
                "type": "NONE",
                "window": false
            },
            "module": 34,
            "x": 3,
            "y": 2
        }
    ],
    "type": "BUILDING",
    "unableToFlipMs": 0,
    "w": 35,
    "x": 0,
    "xSpeed": 0,
    "y": 400,
    "ySpeed": 0
}