[
    {
        "name": "VERSES",
        "gridSize": 2,
        "empires": 2,
        "nests": 1
    },
    {
        "name": "EXTRA_SMALL",
        "gridSize": 2,
        "empires": 3,
        "nests": 5
    },
    {
        "name": "VAST_SMALL",
        "gridSize": 3,
        "empires": 5,
        "nests": 14
    },
    {
        "name": "VAST_MEDIUM",
        "gridSize": 4,
        "empires": 9,
        "nests": 24
    },
    {
        "name": "VAST_LARGE",
        "gridSize": 6,
        "empires": 18,
        "nests": 48
    },
    {
        "name": "EXTRA_LARGE",
        "gridSize": 8,
        "empires": 36,
        "nests": 64
    },
    {
        "name": "INSAINE_LARGE",
        "gridSize": 9,
        "empires": 60,
        "nests": 120
    },
    {
        "name": "WILD_SMALL",
        "gridSize": 3,
        "empires": 3,
        "nests": 18
    },
    {
        "name": "WILD_MEDIUM",
        "gridSize": 4,
        "empires": 5,
        "nests": 32
    },
    {
        "name": "WILD_LARGE",
        "gridSize": 6,
        "empires": 9,
        "nests": 64
    },
    {
        "name": "WILD_EXTRA_SMALL",
        "gridSize": 2,
        "empires": 3,
        "nests": 10
    },
    {
        "name": "VAST_EXTRA_SMALL",
        "gridSize": 2,
        "empires": 3,
        "nests": 8
    },
    {
        "name": "DENSE_SMALL",
        "gridSize": 3,
        "empires": 15,
        "nests": 27
    },
    {
        "name": "DENSE_MEDIUM",
        "gridSize": 4,
        "empires": 27,
        "nests": 48
    },
    {
        "name": "DENSE_LARGE",
        "gridSize": 6,
        "empires": 54,
        "nests": 96
    }
]

